[{"C:\\Users\\nikifang\\Desktop\\\u95f2\u65f6\u63d0\u5347.md": "GB2312"}, {"F:\\blog\\hexo_new_.bat": "ASCII"}, {"C:\\Users\\nikifang\\Desktop\\pop\u9a8c\u7b7e\u6027\u80fd\u4f18\u5316.md": "UTF-8"}, {"C:\\Users\\nikifang\\Desktop\\docker \u968f\u8bb0\u5f55.md": "UTF-8"}, {"F:\\message\\qiweixin\\File\\2019-03\\\u5546\u6237host.txt": "ASCII"}, {"C:\\Users\\nikifang\\Desktop\\\u5de5\u4f5c\u603b\u7ed3\\\u79d2\u6740\u7cfb\u7edf.md": "UTF-8"}, {"D:\\ProgrmFiles\\\u4ebf\u56fe\u56fe\u793a\\edrawmax-pjbd_3987\\\u4f7f\u7528\u8bf4\u660e.txt": "GBK"}, {"F:\\message\\qiweixin\\File\\2019-02\\new 1.txt": "ASCII"}, {"F:\\message\\qiweixin\\File\\2019-02\\\u65b0\u5efa\u6587\u672c\u6587\u6863.txt": "ASCII"}, {"D:\\ProgrmFiles\\Sublime Text 3\\Data\\Packages\\User\\Preferences.sublime-settings": "ASCII"}, {"D:\\ProgrmFiles\\Sublime Text 3\\Data\\Packages\\User\\Default (Windows).sublime-keymap": "ASCII"}, {"C:\\Users\\nikifang\\Desktop\\\u5de5\u4f5c\u603b\u7ed3\\\u5f53\u524d\u7cfb\u7edf\u75db\u70b9\uff0c\u9700\u8981\u63d0\u5347.md": "UTF-8"}, {"F:\\blog\\source\\_posts\\IPFS\u603b\u7ed3.md": "UTF-8"}, {"F:\\blog\\source\\_posts\\Java\u5f02\u6b65\u7f16\u7a0b\u4e4bCompletableFuture.md": "UTF-8"}, {"F:\\blog\\source\\_posts\\\u672c\u5730\u4ed3\u5e93\u8fde\u63a5git\u8fdc\u7a0b\u4ed3\u5e93.md": "UTF-8"}, {"C:\\Users\\nikifang\\Desktop\\\u533a\u5757\u94fe\\solidity\u89e3\u60d1.md": "UTF-8"}, {"E:\\shell\\composer.json": "ASCII"}, {"E:\\shell\\test\\simplexlsxreaq.php": "ASCII"}, {"E:\\shell\\test\\mysql.php": "ASCII"}, {"E:\\dev\\channel_auth_oa\\htdocs\\channel_oa\\autocredit\\carloan.json": "ASCII"}, {"E:\\dev\\channel_auth_oa\\htdocs\\channel_oa\\autocredit\\carloan_result.json": "ASCII"}, {"E:\\dev\\channel_auth_oa\\htdocs\\src\\router\\index.js": "ASCII"}, {"E:\\shell\\vendor\\autoload.php": "ASCII"}, {"E:\\dev\\channel_auth_oa\\htdocs\\package-lock.json": "ASCII"}, {"E:\\shell\\composer.lock": "ASCII"}, {"E:\\shell\\vendor\\phpoffice\\phpexcel\\Examples\\06largescale-with-cellcaching.php": "ASCII"}, {"E:\\shell\\vendor\\phpoffice\\phpexcel\\Examples\\04printing.php": "ASCII"}, {"E:\\shell\\vendor\\phpoffice\\phpexcel\\Examples\\06largescale-xls.php": "ASCII"}, {"E:\\shell\\vendor\\phpoffice\\phpexcel\\Classes\\PHPExcel.php": "ASCII"}, {"E:\\dev\\channel_auth_oa\\htdocs\\channel_oa\\app_switch\\update.json": "ASCII"}, {"E:\\dev\\channel_auth_oa\\htdocs\\channel_oa\\app_switch\\query_list.json": "ASCII"}, {"E:\\dev\\channel_auth_oa\\htdocs\\src\\page\\grayitem\\components\\editDialog.vue": "UTF-8"}, {"E:\\dev\\channel_auth_oa\\htdocs\\src\\page\\graygroup\\components\\editDialog.vue": "UTF-8"}, {"E:\\dev\\channel_auth_oa\\htdocs\\src\\page\\grayfield\\components\\grayList.vue": "UTF-8"}, {"E:\\dev\\channel_auth_oa\\htdocs\\src\\page\\graygroup\\components\\grayList.vue": "UTF-8"}, {"E:\\dev\\channel_auth_oa\\htdocs\\channel_oa\\switch_field\\query_list.json": "ASCII"}, {"E:\\dev\\channel_auth_oa\\htdocs\\channel_oa\\switch_group\\update.json": "ASCII"}, {"E:\\dev\\open_api_itg\\src\\server\\oauth_services.php": "UTF-8"}, {"E:\\dev\\channel_auth_oa\\htdocs\\src\\page\\grayfield\\components\\editDialog.vue": "UTF-8"}, {"E:\\dev\\channel_auth_oa\\htdocs\\src\\page\\grayapp\\components\\appList.vue": "UTF-8"}, {"E:\\dev\\open_api\\src\\application\\classes\\Controller\\Auth.php": "UTF-8"}, {"E:\\test\\10.1.50.208\\work_auth_itg\\src\\server\\order_services.php": "UTF-8"}, {"E:\\dev\\channel_auth_oa\\htdocs\\src\\page\\grayitem\\components\\grayList.vue": "UTF-8"}, {"E:\\dev\\channel_auth_oa\\htdocs\\src\\components\\Common\\SelectApp.vue": "UTF-8"}, {"E:\\dev\\channel_auth_oa\\htdocs\\src\\page\\graygroup\\components\\editAppSwitchDialog.vue": "UTF-8"}, {"E:\\dev\\shell\\work_loan_user\\shell\\verify_bank_card_by_uid.php": "ASCII"}, {"E:\\dev\\channel_auth_oa\\htdocs\\channel_oa\\app_switch\\query_water_list.json": "ASCII"}, {"E:\\dev\\channel_auth_oa\\htdocs\\src\\main.js": "ASCII"}, {"E:\\dev\\channel_auth_oa\\htdocs\\package.json": "ASCII"}, {"E:\\dev\\channel_auth_oa\\htdocs\\src\\store\\index.js": "ASCII"}, {"E:\\dev\\channel_auth_oa\\htdocs\\src\\store\\modules\\grayitem.js": "UTF-8"}, {"E:\\dev\\channel_auth_oa\\htdocs\\src\\store\\modules\\user.js": "UTF-8"}, {"E:\\dev\\channel_auth_oa\\htdocs\\src\\page\\grayitem\\components\\grayListTable.vue": "UTF-8"}, {"E:\\dev\\channel_auth_oa\\htdocs\\src\\page\\grayfield\\components\\grayListTable.vue": "UTF-8"}, {"E:\\dev\\channel_auth_oa\\htdocs\\channel_oa\\switch\\query_list.json": "UTF-8"}, {"E:\\dev\\channel_auth_oa\\htdocs\\src\\page\\grayfield\\index.vue": "UTF-8"}, {"E:\\dev\\channel_auth_oa\\htdocs\\src\\config\\gray.js": "UTF-8"}, {"E:\\dev\\channel_auth_oa\\htdocs\\src\\page\\graygroup\\components\\grayListTable.vue": "UTF-8"}, {"E:\\dev\\channel_auth_oa\\htdocs\\src\\App.vue": "UTF-8"}, {"E:\\dev\\channel_auth_oa\\htdocs\\src\\components\\Common\\SideBar.vue": "UTF-8"}, {"E:\\dev\\channel_auth_oa\\htdocs\\src\\page\\appswitch\\components\\appList.vue": "UTF-8"}, {"E:\\dev\\channel_auth_oa\\htdocs\\src\\page\\appswitch\\index.vue": "UTF-8"}, {"E:\\dev\\channel_auth_oa\\htdocs\\src\\page\\appswitch\\components\\detailDialog.vue": "UTF-8"}, {"E:\\dev\\channel_auth_oa\\htdocs\\src\\page\\appswitch\\components\\appListTable.vue": "UTF-8"}, {"E:\\dev\\channel_auth_oa\\htdocs\\src\\page\\appswitch\\components\\appQueryForm.vue": "UTF-8"}, {"E:\\dev\\channel_auth_oa\\htdocs\\channel_oa\\switch_group\\query_list.json": "UTF-8"}, {"E:\\dev\\channel_auth_oa\\htdocs\\src\\page\\graygroup\\components\\grayQueryForm.vue": "UTF-8"}, {"E:\\dev\\auto_test\\work_loan_itg\\unittest\\online_active\\TableHashTest.php": "UTF-8"}, {"E:\\dev\\channel_auth_oa\\htdocs\\src\\page\\worktable\\components\\gray.vue": "UTF-8"}, {"E:\\dev\\work_loan_itg\\src\\server\\rc_rule\\itg_rc_rule_jxl_pwd_resend_sms_service.php": "UTF-8"}, {"E:\\test\\10.1.50.208\\work_auth_itg\\src\\server\\high_credit_v2_services.php": "UTF-8"}, {"E:\\dev\\channel_auth_oa\\htdocs\\src\\page\\gray\\components\\grayList.vue": "UTF-8"}, {"E:\\dev\\channel_auth_oa\\htdocs\\src\\page\\grayitem\\components\\addDialog.vue": "UTF-8"}, {"E:\\dev\\channel_auth_oa\\htdocs\\src\\page\\graygroup\\components\\addDialog.vue": "UTF-8"}, {"E:\\dev\\channel_auth_oa\\htdocs\\src\\page\\grayitem\\index.vue": "UTF-8"}, {"E:\\dev\\channel_auth_oa\\htdocs\\src\\components\\Common\\SelectUser.vue": "UTF-8"}, {"E:\\java\\tql\\master\\tql-rd\\fql\\publish_web\\src\\main\\web\\src\\components\\SelectUser.vue": "UTF-8"}, {"E:\\test\\10.1.50.208\\work_auth_itg\\src\\server\\common_services.php": "UTF-8"}, {"E:\\dev\\shell\\rc_order_shell\\shell\\auto_marketing_shell.php": "UTF-8"}, {"E:\\dev\\channel_auth_oa\\htdocs\\src\\page\\graygroup\\index.vue": "UTF-8"}, {"E:\\dev\\channel_auth_oa\\htdocs\\src\\assets\\css\\global\\reset.css": "ASCII"}, {"E:\\dev\\channel_auth_oa\\htdocs\\src\\assets\\css\\global\\test.css": "ASCII"}, {"E:\\dev\\channel_auth_oa\\htdocs\\channel_oa\\switch_group\\add.json": "ASCII"}, {"E:\\java\\tql\\master\\tql-rd\\fql\\publish_web\\src\\main\\web\\src\\App.vue": "ASCII"}, {"E:\\dev\\server\\wx\\src\\config\\wx_config.php": "ASCII"}, {"E:\\dev\\channel_auth_oa\\htdocs\\README.md": "ASCII"}, {"E:\\dev\\work_auth_itg\\src\\server\\login_services.php": "ASCII"}, {"E:\\dev\\channel_auth_oa\\htdocs\\config\\dev.env.js": "ASCII"}, {"E:\\dev\\channel_auth_oa\\htdocs\\channel_oa\\switch\\add.json": "ASCII"}, {"null": "ASCII"}, {"E:\\test\\10.1.50.208\\work_loan_auth\\htdocs\\res\\mod_map.js": "ASCII"}, {"E:\\dev\\server\\work_loan\\src\\server\\work_repay\\work_repay_query_for_fql_service.php": "ASCII"}, {"E:\\test\\10.1.50.208\\work_auth_itg\\.hg\\hgrc": "ASCII"}, {"E:\\dev\\channel_auth_oa\\htdocs\\config\\prod.env.js": "ASCII"}, {"E:\\dev\\channel_auth_oa\\htdocs\\config\\test.env.js": "ASCII"}, {"E:\\dev\\channel_auth_oa\\htdocs\\build\\webpack.prod.conf.js": "ASCII"}, {"E:\\dev\\channel_auth_oa\\htdocs\\build\\webpack.dev.conf.js": "ASCII"}, {"E:\\dev\\channel_auth_oa\\htdocs\\build\\build.js": "ASCII"}, {"E:\\dev\\channel_auth_oa\\htdocs\\config\\index.js": "ASCII"}, {"E:\\dev\\channel_auth_oa\\htdocs\\.gitignore": "ASCII"}]